{
    "fluentMethods": true,
    "relationships": [
        {
            "relationshipType": "many-to-one",
            "relationshipName": "application",
            "otherEntityName": "application",
            "otherEntityField": "name"
        }
    ],
    "fields": [
        {
            "fieldName": "name",
            "fieldType": "String"
        },
        {
            "fieldName": "value",
            "fieldType": "String"
        },
        {
            "fieldName": "description",
            "fieldType": "String"
        }
    ],
    "changelogDate": "20170706165801",
    "entityTableName": "key",
    "dto": "no",
    "pagination": "no",
    "service": "no"
}